gloro/__init__.py
gloro/constants.py
gloro/lipschitz_computation.py
gloro/models.py
gloro/utils.py
gloro/layers/__init__.py
gloro/layers/margin_layers.py
gloro/layers/network_layers.py
gloro/relaxations/__init__.py
gloro/relaxations/affinity_sets.py
gloro/relaxations/layers.py
gloro/relaxations/metrics.py
gloro/relaxations/models.py
gloro/training/__init__.py
gloro/training/callbacks.py
gloro/training/losses.py
gloro/training/metrics.py
gloro/training/schedules.py
gloro-1.1.1.dist-info/LICENSE
gloro-1.1.1.dist-info/METADATA
gloro-1.1.1.dist-info/WHEEL
gloro-1.1.1.dist-info/top_level.txt
gloro-1.1.1.dist-info/RECORD
