Metadata-Version: 2.1
Name: gloro
Version: 1.1.1
Summary: library for training globally-robust neural networks
Author: Klas Leino
Author-email: kleino@cs.cmu.edu
Classifier: Programming Language :: Python :: 3
Classifier: License :: OSI Approved :: MIT License
Classifier: Operating System :: OS Independent
Requires-Python: >=3.6
License-File: LICENSE
Requires-Dist: tensorflow (>=2.3)
